monitapi/__init__.py
monitapi/version.py
monitapi/deploy/__init__.py
monitapi/deploy/aws_lambda.py
monitapi/deploy/cloud_functions.py
monitapi/deploy/deployer.py
monitapi/deploy/models.py
monitapi/libs/__init__.py
monitapi/libs/exceptions.py
monitapi/libs/logging.py
monitapi/monitoring/__init__.py
monitapi/monitoring/models.py
monitapi/monitoring/monitor.py
monitapi/notification/__init__.py
monitapi/notification/models.py
monitapi/notification/notification.py
monitapi/notification/libs/__init__.py
monitapi/notification/libs/notifier.py
monitapi/notification/libs/replace_payload.py
monitapi/notification/libs/slack.py
monitapi-0.4.2.dist-info/LICENSE
monitapi-0.4.2.dist-info/METADATA
monitapi-0.4.2.dist-info/WHEEL
monitapi-0.4.2.dist-info/entry_points.txt
monitapi-0.4.2.dist-info/top_level.txt
monitapi-0.4.2.dist-info/RECORD
