Metadata-Version: 2.1
Name: monitapi
Version: 0.4.2
Summary: monitapi is something to monitor API(URL) by a serverless.
Home-page: https://github.com/fealone/monitapi
Author: fealone
Author-email: fealone@lonesec.com
License: UNKNOWN
Platform: UNKNOWN
Classifier: Development Status :: 2 - Pre-Alpha
Classifier: License :: OSI Approved :: GNU Lesser General Public License v3 or later (LGPLv3+)
Classifier: Programming Language :: Python :: 3.7
Classifier: Programming Language :: Python :: 3.8
Classifier: Programming Language :: Python :: 3.9
Requires-Dist: fastapi (>=0.61.1)
Requires-Dist: agraffe (>=0.3.0)
Requires-Dist: pydantic (>=1.6.1)
Requires-Dist: pyyaml (>=5.3.1)
Requires-Dist: aiohttp[speedups] (>=3.6.3)
Requires-Dist: uvicorn[watchdogreload] (>=0.12.1)
Requires-Dist: requests (>=2.24.0)
Requires-Dist: GitPython (>=3.1.9)
